malwareDetector/__init__.py
malwaredetector-0.4.0.dist-info/METADATA
malwaredetector-0.4.0.dist-info/WHEEL
malwaredetector-0.4.0.dist-info/RECORD
