Metadata-Version: 2.4
Name: malwareDetector
Version: 0.4.0
Summary: DEPRECATED - This package has been renamed to islab-malware-detector
Project-URL: Homepage, https://github.com/bolin8017/islab-malware-detector
Project-URL: Documentation, https://github.com/bolin8017/islab-malware-detector/wiki
Project-URL: Repository, https://github.com/bolin8017/islab-malware-detector.git
Project-URL: NewPackage, https://pypi.org/project/islab-malware-detector/
Author-email: PO-LIN LAI <bolin8017@gmail.com>
License: MIT
Keywords: deprecated,detector,framework,malware,security
Classifier: Development Status :: 7 - Inactive
Classifier: Intended Audience :: Developers
Classifier: License :: OSI Approved :: MIT License
Classifier: Programming Language :: Python :: 3.12
Classifier: Programming Language :: Python :: 3.13
Requires-Python: >=3.12
Requires-Dist: islab-malware-detector>=0.3.1
